dragg_comp/__init__.py
dragg_comp/agent.py
dragg_comp/envs.py
dragg_comp/player.py
dragg_comp/player_plot.py
dragg_comp/rl_aggregator.py
dragg_comp-0.5.1.dist-info/LICENSE
dragg_comp-0.5.1.dist-info/METADATA
dragg_comp-0.5.1.dist-info/WHEEL
dragg_comp-0.5.1.dist-info/top_level.txt
dragg_comp-0.5.1.dist-info/RECORD
