Metadata-Version: 2.1
Name: dragg-comp
Version: 0.5.1
Author: Aisling Pigott and Jacob Kravits
Author-email: aisling.pigott@colorado.edu
License: MIT
Classifier: Programming Language :: Python :: 3
Classifier: License :: OSI Approved :: MIT License
Classifier: Operating System :: OS Independent
License-File: LICENSE
Requires-Dist: asyncio
Requires-Dist: aioredis
Requires-Dist: gym
Requires-Dist: pathos
Requires-Dist: datetime
Requires-Dist: async-timeout
Requires-Dist: dragg
Requires-Dist: cvxopt
Requires-Dist: kaleido
